[
  {
    "label": "アクセルリンク",
    "cost": "2",
    "page": "PW 89",
    "desc": ""
  },
  {
    "label": "イナーシャルブースト",
    "cost": "3",
    "page": "PW 89",
    "desc": ""
  },
  {
    "label": "ウェポンコントロール",
    "cost": "3",
    "page": "PW 89",
    "desc": ""
  },
  {
    "label": "エイムプラス",
    "cost": "1",
    "page": "PW 89",
    "desc": ""
  },
  {
    "label": "エンハンスアーマー",
    "cost": "2",
    "page": "PW 89",
    "desc": ""
  },
  {
    "label": "エンハンスウェポン",
    "cost": "3",
    "page": "PW 89",
    "desc": ""
  },
  {
    "label": "オーバークロック",
    "cost": "3",
    "page": "PW 89",
    "desc": ""
  },
  {
    "label": "ガードモーション",
    "cost": "2",
    "page": "PW 90",
    "desc": ""
  },
  {
    "label": "クイックアシスト",
    "cost": "2",
    "page": "PW 90",
    "desc": ""
  },
  {
    "label": "クイックドロー",
    "cost": "3",
    "page": "PW 90",
    "desc": ""
  },
  {
    "label": "クイックリロード",
    "cost": "2",
    "page": "PW 90",
    "desc": ""
  },
  {
    "label": "クリティカルショット",
    "cost": "2",
    "page": "PW 90",
    "desc": ""
  },
  {
    "label": "ジャンプアップ",
    "cost": "2",
    "page": "PW 90",
    "desc": ""
  },
  {
    "label": "セカンドインパクト",
    "cost": "2",
    "page": "PW 90",
    "desc": ""
  },
  {
    "label": "ターゲッティング",
    "cost": "1",
    "page": "PW 90",
    "desc": ""
  },
  {
    "label": "タクティカルステップ",
    "cost": "2",
    "page": "PW 91",
    "desc": ""
  },
  {
    "label": "チャージショット",
    "cost": "1",
    "page": "PW 91",
    "desc": ""
  },
  {
    "label": "ディスターベンス",
    "cost": "2",
    "page": "PW 91",
    "desc": ""
  },
  {
    "label": "フィールドオブルーラー",
    "cost": "3",
    "page": "PW 91",
    "desc": ""
  },
  {
    "label": "ブレイクフォール",
    "cost": "1",
    "page": "PW 91",
    "desc": ""
  },
  {
    "label": "プロクレイム",
    "cost": "3",
    "page": "PW 91",
    "desc": ""
  },
  {
    "label": "マルチロック",
    "cost": "3",
    "page": "PW 91",
    "desc": ""
  },
  {
    "label": "ラピッドムーブ",
    "cost": "1",
    "page": "PW 91",
    "desc": ""
  },
  {
    "label": "イラプションバレット",
    "cost": "1",
    "page": "VI 48",
    "desc": ""
  },
  {
    "label": "インサイトアイ",
    "cost": "2",
    "page": "VI 48",
    "desc": ""
  },
  {
    "label": "エリアインヴェイド",
    "cost": "2",
    "page": "VI 48",
    "desc": ""
  },
  {
    "label": "オーバーライド",
    "cost": "2",
    "page": "VI 48",
    "desc": ""
  },
  {
    "label": "グレイズウェポン",
    "cost": "3",
    "page": "VI 48",
    "desc": ""
  },
  {
    "label": "コンセントレイト",
    "cost": "3",
    "page": "VI 48",
    "desc": ""
  },
  {
    "label": "コンタクトショット",
    "cost": "2",
    "page": "VI 48",
    "desc": ""
  },
  {
    "label": "ジャストリロード",
    "cost": "3",
    "page": "VI 49",
    "desc": ""
  },
  {
    "label": "ストリームライン",
    "cost": "2",
    "page": "VI 49",
    "desc": ""
  },
  {
    "label": "ディープブレス",
    "cost": "2",
    "page": "VI 49",
    "desc": ""
  },
  {
    "label": "テクニカルキャンセル",
    "cost": "2",
    "page": "VI 49",
    "desc": ""
  },
  {
    "label": "ドローアテンション",
    "cost": "3",
    "page": "VI 49",
    "desc": ""
  },
  {
    "label": "ビールドミラージュ",
    "cost": "2",
    "page": "VI 49",
    "desc": ""
  },
  {
    "label": "プレシャスレゾナンス",
    "cost": "2",
    "page": "VI 49",
    "desc": ""
  },
  {
    "label": "ポインターセット",
    "cost": "1",
    "page": "VI 49",
    "desc": ""
  }
]
